MANIFEST.in
README.md
setup.py
django_extra_migrations/__init__.py
django_extra_migrations/migrations.py
django_extra_migrations/models.py
django_extra_migrations.egg-info/PKG-INFO
django_extra_migrations.egg-info/SOURCES.txt
django_extra_migrations.egg-info/dependency_links.txt
django_extra_migrations.egg-info/requires.txt
django_extra_migrations.egg-info/top_level.txt