Metadata-Version: 1.1
Name: django-extra-migrations
Version: 0.0.5
Summary: Extra migration classes for django
Home-page: https://github.com/xacce/django_extra_migrations
Author: Xacce
Author-email: thiscie@gmail.com
License: MIT
Keywords: d,j,a,n,g,o, ,m,i,g,r,a,t,i,o,n,s, ,p,e,r,m,i,s,s,i,o,n,s, ,m,o,d,e,l,s
Platform: UNKNOWN
Classifier: Development Status :: 4 - Beta
Classifier: Intended Audience :: Developers
Classifier: License :: OSI Approved :: MIT License
Classifier: Programming Language :: Python :: 2.6
Classifier: Programming Language :: Python :: 2.7
